<?xml version="1.0"?>
<?mso-application progid="Excel.Sheet"?>
<Workbook xmlns="urn:schemas-microsoft-com:office:spreadsheet"
 xmlns:o="urn:schemas-microsoft-com:office:office"
 xmlns:x="urn:schemas-microsoft-com:office:excel"
 xmlns:ss="urn:schemas-microsoft-com:office:spreadsheet"
 xmlns:html="http://www.w3.org/TR/REC-html40">
 
 <Worksheet ss:Name="Others">
  <Table ss:ExpandedColumnCount="2" ss:ExpandedRowCount="491" x:FullColumns="1"
   x:FullRows="1" ss:DefaultRowHeight="15">
   
   <Row>
    <Cell><Data>LOLIPOP</Data></Cell>
    <Cell><Data>30 DR AMBEDKAR RD, ASHOK NAGAR,MAIN RD, 600001</Data></Cell>
   </Row>
   <Row>
    <Cell><Data>WILLIAM PENN</Data></Cell>
    <Cell><Data>UNIT NO. F-44 1ST FLOOR, PHOENIX MARKETCITY NO.142,VELACHERY MAIN ROAD VELACHERY, 600042</Data></Cell>
   </Row>
   <Row>
    <Cell><Data>CHHOTABHAI RETAILING</Data></Cell>
    <Cell><Data>G-40B GROUND FLOOR, PHONIX MARKET CITY,142 VELACHERY MAIN ROAD,VELACHERY, 600042</Data></Cell>
   </Row>
   <Row>
    <Cell><Data>ESKE</Data></Cell>
    <Cell><Data>PHOENIX MARKET CITY MALL, UG-15 NO.142, MAIN ROAD,VELACHERY, 600042</Data></Cell>
   </Row>
   <Row>
    <Cell><Data>AMMU HANDIKRAFTS</Data></Cell>
    <Cell><Data>NO61, FIVE RATHS SHOPPING COMPLEX, MAMALLAPURAM,THIRUKKALUKUNDRAM, 603104</Data></Cell>
   </Row>
   <Row>
    <Cell><Data>ARCHIES GALLERY</Data></Cell>
    <Cell><Data>SHOP NO. S23 / 2ND, FLOOR, 142 VELACHERY ROAD, VELACHERY, 600042</Data></Cell>
   </Row>
   <Row>
    <Cell><Data>HARYANA HANDLOOM</Data></Cell>
    <Cell><Data>SHOP NO 107, SPENCER PLAZA, PHASE II,ANNA SALAI, 600002</Data></Cell>
   </Row>
   <Row>
    <Cell><Data>HARYANA HANDLOOM</Data></Cell>
    <Cell><Data>OLD 9 PONDY BAZAAR, NEW 66/3 THEAGARAYA ROAD,T. NAGAR, 600017</Data></Cell>
   </Row>
   <Row>
    <Cell><Data>CAPITAL PHOTO SERVICE</Data></Cell>
    <Cell><Data>SPENCER 769 ANNASALAI, 600002</Data></Cell>
   </Row>
   <Row>
    <Cell><Data>CAPITAL PHOTO SERVICE</Data></Cell>
    <Cell><Data>CITY CENTER SHOP NO 10 &amp; 11, DR RADHA KRISHNA ROAD,MYLAORE, 600004</Data></Cell>
   </Row>
   <Row>
    <Cell><Data>CAPITAL PHOTO SERVICE</Data></Cell>
    <Cell><Data>AMPA SKYWALK 3RD FLR, NELSON MANICKAM ROAD,AMINJIKARAI, 600029</Data></Cell>
   </Row>
   <Row>
    <Cell><Data>UNIQUE HOUSE OF CASHMERE</Data></Cell>
    <Cell><Data>SHOP NO S-106 SECOND FLOOR, PHASE-III SPENCERS PLAZA,9 ANNA SALAI, 600002</Data></Cell>
   </Row>
   <Row>
    <Cell><Data>ANANDRAM DEVELOPERS PVT LTD</Data></Cell>
    <Cell><Data>45 &amp; 47 ARCOT ROAD SALIGRAMAM, 600093</Data></Cell>
   </Row>
   <Row>
    <Cell><Data>CHHOTABHAI RETAILING</Data></Cell>
    <Cell><Data>LEGO G40/A 142 VELACHERY MAIN ROAD, VELACHERY, 600042</Data></Cell>
   </Row>
   <Row>
    <Cell><Data>CHHOTABHAI RETAILING</Data></Cell>
    <Cell><Data>PLOT NO. 172 SRIDEVIKUPPAM, MAIN ROAD PREETHI TOWERS,VALASARAVAKKAM, 600087</Data></Cell>
   </Row>
   <Row>
    <Cell><Data>JANAPRIYA BUILDERS</Data></Cell>
    <Cell><Data>34 PONDY, BAZAAR, THYGARAYANAGAR HO, 600017</Data></Cell>
   </Row>
   <Row>
    <Cell><Data>VFS GLOBAL SERVICES PVT LTD</Data></Cell>
    <Cell><Data>SHOP NO 5 FIRST FLR, SUN PLAZA G N CHETTY RD, 600006</Data></Cell>
   </Row>
   <Row>
    <Cell><Data>ARCHIES GALLERY</Data></Cell>
    <Cell><Data>SHOP NO.224 2ND FLR NO-183, N S K SALAI VADAPALANI,VADAPALANI, 600026</Data></Cell>
   </Row>
   <Row>
    <Cell><Data>ARCHIES GALLERY</Data></Cell>
    <Cell><Data>SHOP NO.F-131A III PHASE FIRST FLR, 768 ANNA SALAI, 122002</Data></Cell>
   </Row>
   <Row>
    <Cell><Data>HI-TECH ENTERPRISESS</Data></Cell>
    <Cell><Data>NO:62/1 1ST FLOOR, VADIVEL STREET PERAMBUR, 600011</Data></Cell>
   </Row>
   <Row>
    <Cell><Data>FOCUS ART GALLERY</Data></Cell>
    <Cell><Data>NO 59 TTK ROAD, ALWARPET, 600018</Data></Cell>
   </Row>
   <Row>
    <Cell><Data>RAJMANDIR SELECTION</Data></Cell>
    <Cell><Data>359 SHRINGAR COMPLEX, MINT STREET SHOWCARPET, 600079</Data></Cell>
   </Row>
   <Row>
    <Cell><Data>KAMATCHI STORES</Data></Cell>
    <Cell><Data>NO. 105, DURAIARASAN STREET, SALIGRAMAM, 600093</Data></Cell>
   </Row>
   <Row>
    <Cell><Data>PLANET M</Data></Cell>
    <Cell><Data>EXPRESS AVENUE COMMERCIAL COMPLEX, NO-49,50,L WHITE ROAD,ROYAPETTAH, 600014</Data></Cell>
   </Row>
   <Row>
    <Cell><Data>R M X JOSS</Data></Cell>
    <Cell><Data>S-129 EXPRESS AVENUE MALL, CLUB HOUSE ROAD, 600002</Data></Cell>
   </Row>
   <Row>
    <Cell><Data>PRODIGI</Data></Cell>
    <Cell><Data>NEW NO 76 OLD NO 104 DR RADHAKRISHNAN, SALAI,MYLAPORE, 600004</Data></Cell>
   </Row>
   <Row>
    <Cell><Data>SOCOMEC UPS INDIA PVT LTD</Data></Cell>
    <Cell><Data>B1, 2ND FLOOR, THIRU VI-KA, INDUSTRIAL ESTATE, GUINOY, 600032</Data></Cell>
   </Row>
   <Row>
    <Cell><Data>G R CASHMERE SHAWLS BOUTIQUE</Data></Cell>
    <Cell><Data>NO PHASE II 2ND FLOOR, SPENCER PLAZA SHOP NO 68E,NO 769 ANNASALAI, 600002</Data></Cell>
   </Row>
   <Row>
    <Cell><Data>PHOENIX FITNESS STUDIO</Data></Cell>
    <Cell><Data>128, III FLOOR, ARCHS BISHOP, ARULAPPA TOWERS,SANTHOME HIGH ROAD, 600004</Data></Cell>
   </Row>
   <Row>
    <Cell><Data>BHAGAWATHI STATIONERS</Data></Cell>
    <Cell><Data>G9, ALSA MALL, MONTIETH ROAD, 600008</Data></Cell>
   </Row>
   <Row>
    <Cell><Data>WILLIAM PENN</Data></Cell>
    <Cell><Data>SHOP NO.S-023, UPPER GROUND FLOOR, EXPRESS AVENUE,49-50, WHITES ROAD, 600014</Data></Cell>
   </Row>
   <Row>
    <Cell><Data>HOROLOGY</Data></Cell>
    <Cell><Data>SHOP NO.S-002 AND S 003, GROUND FLOOR,EXPRESS AVENUE,WHITES ROAD, 600014</Data></Cell>
   </Row>
   <Row>
    <Cell><Data>HOROLOGY</Data></Cell>
    <Cell><Data>27, HOTEL TAJ CROMANDEL, M G ROAD, 600034</Data></Cell>
   </Row>
   <Row>
    <Cell><Data>ARCHIES GALLERY</Data></Cell>
    <Cell><Data>14, MANJULA COMPLEX, ECR ROAD,KAPALEESHWAR NAGAR, NEELANKARAI, 600041</Data></Cell>
   </Row>
   <Row>
    <Cell><Data>ARCHIES GALLERY</Data></Cell>
    <Cell><Data>G-1, NO.81,LUZ CHURCH ROAD, PALANISAMY APARTMENT,MYLAPORE, 600004</Data></Cell>
   </Row>
   <Row>
    <Cell><Data>MOKSH</Data></Cell>
    <Cell><Data>EXPRESS AVENUE, SHOP NO.240,NO.49, SOL, WHITES ROAD, 600014</Data></Cell>
   </Row>
   <Row>
    <Cell><Data>ANHAAR ARTS EMPORIUM</Data></Cell>
    <Cell><Data>F-104, 1ST FLOOR, PHASE III, 769, ANNA SALAI, 600002</Data></Cell>
   </Row>
   <Row>
    <Cell><Data>BULCHEE -EXPRESS AVENEUE</Data></Cell>
    <Cell><Data>55, EXPRESS AVENUE MALL, WHITES ROAD, 600014</Data></Cell>
   </Row>
   <Row>
    <Cell><Data>JEYACHANDRAN INDUSTRIES</Data></Cell>
    <Cell><Data>10/20, 1ST FLOOR, HONG-KONG COMPLEX, RAMANATHAN STREET,T NAGAR, 600017</Data></Cell>
   </Row>
   <Row>
    <Cell><Data>INDIAS TOUCH</Data></Cell>
    <Cell><Data>308, 3RD FLOOR,EXPRESS AVENUE, CLUB HOUSE ROAD, 600002</Data></Cell>
   </Row>
   <Row>
    <Cell><Data>NASSCOM</Data></Cell>
    <Cell><Data>FLAT G-1AMEEN MANOR, NO.138, NUNGAMBAKKAM HIGH ROAD,NUNGAMBAKKAM, 600034</Data></Cell>
   </Row>
   <Row>
    <Cell><Data>CELESTIEL</Data></Cell>
    <Cell><Data>27, OMR RAJIV GANDHI SALAI, SRINIVASA NAGAR, 600041</Data></Cell>
   </Row>
   <Row>
    <Cell><Data>ANGELS</Data></Cell>
    <Cell><Data>AC-15, IIND AVENUE BLUE STAR, ANNA NAGAR, 600040</Data></Cell>
   </Row>
   <Row>
    <Cell><Data>UNIQUE GIFTS</Data></Cell>
    <Cell><Data>ANNA INTERNATIONAL TERMINAL, CHENNAI AIRPORT, 600027</Data></Cell>
   </Row>
   <Row>
    <Cell><Data>VARASIDHI</Data></Cell>
    <Cell><Data>VARASIDHI, 29, BALFOUR ROAD, KELLYS, 600010</Data></Cell>
   </Row>
   <Row>
    <Cell><Data>EDITIONS - PEN OF THE WORLD</Data></Cell>
    <Cell><Data>SHOP NO S -16 GROUND FLOOR, EXPRESS AVENUE MALL,49 - 50 L WHITES ROAD ROYAPETTAH, 600014</Data></Cell>
   </Row>
   <Row>
    <Cell><Data>SINGAPORE SHOPPEE</Data></Cell>
    <Cell><Data>NO 1065/1067, O 356/357,T H ROAD, 600021</Data></Cell>
   </Row>
   <Row>
    <Cell><Data>KRYSTAL KRAFTS</Data></Cell>
    <Cell><Data>NO 30/57, T T K ROAD,ALWARPET, 600018</Data></Cell>
   </Row>
   <Row>
    <Cell><Data>N2H</Data></Cell>
    <Cell><Data>26/10, KASTURI BHAI NAGAR, 3RD CROSS, ADYAR,(OPP TO NALLI SILK SAREES), 600020</Data></Cell>
   </Row>
   <Row>
    <Cell><Data>MOMENTZ</Data></Cell>
    <Cell><Data>SHOP NO.SL-12A, BASEMENT I, 49-50, WHITES ROAD, ROYAPETTAH,EXPRESS AVENUE, 600014</Data></Cell>
   </Row>
   <Row>
    <Cell><Data>N2H (A UNIT OF APEX LINKS)</Data></Cell>
    <Cell><Data>12, CONRAN SMITH ROAD, GOPALAPURAM, 600086</Data></Cell>
   </Row>
   <Row>
    <Cell><Data>HEALING MATRIX</Data></Cell>
    <Cell><Data>G-2B, BROOKLYN BUSINESS CENTRE, NO.103-105, POONAMALLE HIGHR ROAD, 600084</Data></Cell>
   </Row>
   <Row>
    <Cell><Data>N2H</Data></Cell>
    <Cell><Data>NEW NUMBER 20, CO-OPERATIVE COLONY,SRIRAM NAGAR,CHAMIERS ROAD, 600018</Data></Cell>
   </Row>
   <Row>
    <Cell><Data>N2H</Data></Cell>
    <Cell><Data>KIOSK NO.5, GROUND FLOOR, EXPRESS AVENUE MALL,49/50L, WHITES ROAD ,ROYAPETTAH, 600014</Data></Cell>
   </Row>
   <Row>
    <Cell><Data>N2H</Data></Cell>
    <Cell><Data>AH-6, SHANTHI COLONY, OPP GANGOTREE,ANNA NAGAR, 600040</Data></Cell>
   </Row>
   <Row>
    <Cell><Data>AARASZ</Data></Cell>
    <Cell><Data>G-97, GROUND FLOOR, PHASE II, SPENCER PLAZA ,769, ANNA SALAI,THOUSAND LIGHTS, 600002</Data></Cell>
   </Row>
   <Row>
    <Cell><Data>SOWBARNIKAS COLLECTIONS</Data></Cell>
    <Cell><Data>123, ISPHANI CENTRE, NUNGAMBAKKAM, HIGH ROAD ,NUNGAMBAKKAM, 600006</Data></Cell>
   </Row>
   <Row>
    <Cell><Data>CHASE ART BAZZAR</Data></Cell>
    <Cell><Data>F-91 SPENCER PLAZA, 769 ANNA SALAI, 600002</Data></Cell>
   </Row>
   <Row>
    <Cell><Data>INFLOT</Data></Cell>
    <Cell><Data>SHOP NO. 43A, EXPRESS AVENUE MALL, 49,50 LWHITES ROAD,ROYAPETHA, 600016</Data></Cell>
   </Row>
   <Row>
    <Cell><Data>K.M.S.DIGITAL CAMERA PALACE</Data></Cell>
    <Cell><Data>NO.1 P.H. ROAD STORE NO S-222, 2ND FLOOR AMINJAKARAI AMPA,SKY WALK MALL, 600029</Data></Cell>
   </Row>
   <Row>
    <Cell><Data>LAXMI MOTORS</Data></Cell>
    <Cell><Data>NO.14, POONAMALLEE TRUNK ROAD, KARYANCHAVADI, 600056</Data></Cell>
   </Row>
   <Row>
    <Cell><Data>AVA MERCHANDISING SOLUTIONS PVT LTD</Data></Cell>
    <Cell><Data>CHENNAI INTERNATIONAL AIRPORT, DOMESTIC TERMINAL,ARRIVAL HALL, 600027</Data></Cell>
   </Row>
   <Row>
    <Cell><Data>KUMAR AGENCY</Data></Cell>
    <Cell><Data>OLD NO 29 NEW NO 84 RAJAM, APTS 1ST AVENUE ASHOK NAGAR, 600083</Data></Cell>
   </Row>
   <Row>
    <Cell><Data>ABSOLUTE BPO PRIVATE LIMITED</Data></Cell>
    <Cell><Data>OLD NO 4 NEW NO 9, ABDUL KAREEM LANE TRIPLICANE, 600005</Data></Cell>
   </Row>
   <Row>
    <Cell><Data>ARCHIES GALLERY</Data></Cell>
    <Cell><Data>365. MOUNT ROAD, ANNA SALAI TEYNAMPET, 600018</Data></Cell>
   </Row>
   <Row>
    <Cell><Data>ARCHIES GALLERY</Data></Cell>
    <Cell><Data>SHOP NO.3,GR FLR, NO.70/2,&amp;114A &amp; 114B, PAPER MILLS ROAD, PERAMBUR, 600011</Data></Cell>
   </Row>
   <Row>
    <Cell><Data>SHAREWARE DREAMS</Data></Cell>
    <Cell><Data>74 KILPAUK GARDEN ROAD, KILPAUK, 600010</Data></Cell>
   </Row>
   <Row>
    <Cell><Data>SATGURU'S</Data></Cell>
    <Cell><Data>NEW NO - 5, OLD NO - 47/1,STERLING -, AVENUE,GR FLR,NUNGAMBAKKAM, 600034</Data></Cell>
   </Row>
   <Row>
    <Cell><Data>PLANET M</Data></Cell>
    <Cell><Data>NEW NO 283, OLD NO 123, TTK ROAD, NEAR, HOTEL SHERATON ADYAR GATE,ALWARPET, 600018</Data></Cell>
   </Row>
   <Row>
    <Cell><Data>DAR BROTHERS</Data></Cell>
    <Cell><Data>34/10 OTHAVADAI STREET, MAMALLAPURAM, 603104</Data></Cell>
   </Row>
   <Row>
    <Cell><Data>KRISHNA THULASI</Data></Cell>
    <Cell><Data>98 PONDY BAZAAR, T NAGAR, 600017</Data></Cell>
   </Row>
   <Row>
    <Cell><Data>GOLDEN CASTLE</Data></Cell>
    <Cell><Data>G-9A SPENCER PLAZA, 769 ANNA SALAI, 600002</Data></Cell>
   </Row>
   <Row>
    <Cell><Data>CRAFTS INN</Data></Cell>
    <Cell><Data>15 B GRND FLOOR, SPENCER PLAZA, MOUNT ROAD, 600002</Data></Cell>
   </Row>
   <Row>
    <Cell><Data>KHUZEMA MAMUWALA &amp; CO PVT LTD</Data></Cell>
    <Cell><Data>72, KUTCHERY ROAD, MYLAPORE, 600004</Data></Cell>
   </Row>
   <Row>
    <Cell><Data>CENTRAL COTTAGE EMPORIUM</Data></Cell>
    <Cell><Data>TEMPLE TOWERS, 1ST FLOOR, 476, ANNA SALAI NANDANAM, 600035</Data></Cell>
   </Row>
   <Row>
    <Cell><Data>KASHMIR ART PALACE</Data></Cell>
    <Cell><Data>156 MOUNT ROAD, 600002</Data></Cell>
   </Row>
   <Row>
    <Cell><Data>KASHMIR GIFT EMPORIUM</Data></Cell>
    <Cell><Data>HOTEL SAVERA, 69,RADHA KRISHNAN ROAD,MYLAPORE, 600004</Data></Cell>
   </Row>
   <Row>
    <Cell><Data>ORIENTAL ARTS</Data></Cell>
    <Cell><Data>CENTURY PLAZA, 560/562 MOUNT RD TEYNAMPT,ORIENTALARTS-CHENNAI@HOTMAIL.COM, 600018</Data></Cell>
   </Row>
   <Row>
    <Cell><Data>NEW KASHMIR ARTS &amp; CRAFTS</Data></Cell>
    <Cell><Data>NO.171, MOUNT ROAD,NEWKASH@HOTMAIL.COM, 600002</Data></Cell>
   </Row>
   <Row>
    <Cell><Data>APPARAO GALLERIES</Data></Cell>
    <Cell><Data>7 WALLACE GARDEN, 3 RD STREET, OPP TAJ COROMONDAL,GALLERY@GIASMD01.VSNL.NET.IN, 600006</Data></Cell>
   </Row>
   <Row>
    <Cell><Data>RENU'S GALLERY</Data></Cell>
    <Cell><Data>48 DR.B.N.ROAD, MAHBUBANI TOWER,T.NAGAR, 600017</Data></Cell>
   </Row>
   <Row>
    <Cell><Data>RUPKALI</Data></Cell>
    <Cell><Data>995 B,IIND AVENUE, ANNANAGAR WEST, 600040</Data></Cell>
   </Row>
   <Row>
    <Cell><Data>ANMOL</Data></Cell>
    <Cell><Data>SHOP NO 160, FOUNTAIN PLAZA, PANTHEON ROAD, EGMORE, 600008</Data></Cell>
   </Row>
   <Row>
    <Cell><Data>ANKUR</Data></Cell>
    <Cell><Data>SHOP NO 189, FOUNTAIN PLAZA, PANTHEON ROAD, EGMORE, 600008</Data></Cell>
   </Row>
   <Row>
    <Cell><Data>G A M SHAH</Data></Cell>
    <Cell><Data>KASHMIR HANDICRAFTS EMPORIUM GIFT SHOP, HOTEL AMBICA EMPIRE,79 100 FT ROAD VADAPALANI, 600026</Data></Cell>
   </Row>
   <Row>
    <Cell><Data>INDIAN ARTS MUSEUM</Data></Cell>
    <Cell><Data>AGURCHAND MANSION, 151 MOUNT ROAD, 600002</Data></Cell>
   </Row>
   <Row>
    <Cell><Data>CAUVERY KARNATAKA STE A &amp; C EM</Data></Cell>
    <Cell><Data>5 LIC BUILDING, ANNA SALAI MOUNT ROAD, 600002</Data></Cell>
   </Row>
   <Row>
    <Cell><Data>AESTHETICS</Data></Cell>
    <Cell><Data>SHOP NO 15 AARTI ARCADE, 86 DR RADHAKRISHNAN ROAD,AESTHETICSIN@YAHOO.COM, 600004</Data></Cell>
   </Row>
   <Row>
    <Cell><Data>VICTORIA TECHNICAL INSTITUTE</Data></Cell>
    <Cell><Data>765 ANNA ROAD, 600002</Data></Cell>
   </Row>
   <Row>
    <Cell><Data>RUPKALA</Data></Cell>
    <Cell><Data>191, ANNA SALAI, 600006</Data></Cell>
   </Row>
   <Row>
    <Cell><Data>MAN MANDIR SILKS AND SAREES</Data></Cell>
    <Cell><Data>&quot;PLATINUM&quot;, #32,KHADER NAWAZ KHAN ROAD, 600006</Data></Cell>
   </Row>
   <Row>
    <Cell><Data>PALLAVI GARDEN VARELI</Data></Cell>
    <Cell><Data>289 PURASAWAKKAM HIGH RD, 600007</Data></Cell>
   </Row>
   <Row>
    <Cell><Data>POOMPUHAR SHOW ROOM</Data></Cell>
    <Cell><Data>108, ANNA SALAI,NEXT TO HIGGEBOTHAM BOOKSTALL,POOMHANDI@HOTMAIL.COM, 600002</Data></Cell>
   </Row>
   <Row>
    <Cell><Data>KALPA DRUMA DIVN. OF EXIND CORPN.</Data></Cell>
    <Cell><Data>61, CATHEDRAL ROAD,EXIND@VSNL.COM, 600086</Data></Cell>
   </Row>
   <Row>
    <Cell><Data>B.M.SILK SAREES</Data></Cell>
    <Cell><Data>5,NORTH MADA STREET, MYLAPORE,MAIL@B.M.SILKSAREESCHENNAI.COM, 600004</Data></Cell>
   </Row>
   <Row>
    <Cell><Data>THE CONTEMPORARY WINDOW</Data></Cell>
    <Cell><Data>H-137/3, SECOND AVENUE, BESANT NAGAR,OPP.SPENCER'S,ARTSANDCRAFTS@TCW.CO.IN, 600090</Data></Cell>
   </Row>
   <Row>
    <Cell><Data>INDIAN ARTS EMPORIUM</Data></Cell>
    <Cell><Data>AGURCHAND MANSION, 152, MOUNT ROAD, 600002</Data></Cell>
   </Row>
   <Row>
    <Cell><Data>TIBETIAN ART GALLERY</Data></Cell>
    <Cell><Data>16-B GROUND FLOOR, SPENCER PLAZA,MOUNT ROAD, 600002</Data></Cell>
   </Row>
   <Row>
    <Cell><Data>COTTAGE EMPORIUM</Data></Cell>
    <Cell><Data>G-105, GROUND FLOOR , II PHASE , SPENCER PLAZA , 600002</Data></Cell>
   </Row>
   <Row>
    <Cell><Data>BOBBY</Data></Cell>
    <Cell><Data>3/84,PONDY BAZAR, T.NAGAR, 600017</Data></Cell>
   </Row>
   <Row>
    <Cell><Data>NEW CHOLAN MATCHING</Data></Cell>
    <Cell><Data>247 R K MUTT ROAD, OPP MYLAI TANK,MYLAPORE, 600004</Data></Cell>
   </Row>
   <Row>
    <Cell><Data>TIME LINKS</Data></Cell>
    <Cell><Data>1/2 B BLOCK, ANNA NAGAR EAST, 600102</Data></Cell>
   </Row>
   <Row>
    <Cell><Data>THILAKAM &amp; CO</Data></Cell>
    <Cell><Data>79, M T H ROAD,VILLIVAKKAM, 600049</Data></Cell>
   </Row>
   <Row>
    <Cell><Data>THILAKAM &amp; CO</Data></Cell>
    <Cell><Data>1 M T H ROAD, AMBATTUR, 600053</Data></Cell>
   </Row>
   <Row>
    <Cell><Data>MOHINI CREATION</Data></Cell>
    <Cell><Data>F 60A IST FLOOR PHASE II, SPENCER PLAZA,769 MOUNT ROAD, 600002</Data></Cell>
   </Row>
   <Row>
    <Cell><Data>FOTO INDIA</Data></Cell>
    <Cell><Data>JHAVER PLAZA, 1 A, NUNGAMBAKKAM HIGH ROAD, 600034</Data></Cell>
   </Row>
   <Row>
    <Cell><Data>REHANE</Data></Cell>
    <Cell><Data>STORE NO 10 SAXAMS GARDEN, NO 10 KHADER NAWAZ KHAN ROAD,NUNGMABAKKAM, 600034</Data></Cell>
   </Row>
   <Row>
    <Cell><Data>COTTAGE ARTS EMPORIUM</Data></Cell>
    <Cell><Data>29 TTK ROAD, 600018</Data></Cell>
   </Row>
   <Row>
    <Cell><Data>CHINAR</Data></Cell>
    <Cell><Data>G - 52 GROUND FLOOR, SPENCER PLAZA, PHASE 2,769 ANNA SALAI, 600002</Data></Cell>
   </Row>
   <Row>
    <Cell><Data>RANGOLI</Data></Cell>
    <Cell><Data>30, SPURTANK ROAD,CHEPET, 600031</Data></Cell>
   </Row>
   <Row>
    <Cell><Data>RIGHT CHOICE</Data></Cell>
    <Cell><Data>SHOP NO 5 &amp; 6 GOKUL ARCADE, NO 2 SARDAR PATEL ROAD,ADYAR, 600020</Data></Cell>
   </Row>
   <Row>
    <Cell><Data>ARTISAN'S</Data></Cell>
    <Cell><Data>AGURCHAND MANSION, 151 MOUNT ROAD, 600002</Data></Cell>
   </Row>
   <Row>
    <Cell><Data>GOLDEN LAND</Data></Cell>
    <Cell><Data>S NO F-66 2 PHASE, 1ST FLOOR,SPENCER PLAZA,MOUNT ROAD, 600002</Data></Cell>
   </Row>
   <Row>
    <Cell><Data>CARS INDIA LTD</Data></Cell>
    <Cell><Data>16 &amp; 17 INDUSTRIAL ESTATE, AMBATTUR,CARSI@MD2.VSNL.NET.IN, 600058</Data></Cell>
   </Row>
   <Row>
    <Cell><Data>CARS INDIA LTD</Data></Cell>
    <Cell><Data>17 LATTICE BRIDGE RD, ADYAR,CARSI@MD2.VSNL.NET.IN, 600020</Data></Cell>
   </Row>
   <Row>
    <Cell><Data>JANATA TIMBER DEPOT</Data></Cell>
    <Cell><Data>NO 589, ANNA SALAI,MOUNT ROAD, 600006</Data></Cell>
   </Row>
   <Row>
    <Cell><Data>NEW KASHMIR ARTS &amp; CRAFTS</Data></Cell>
    <Cell><Data>HOTEL CHOLA SHERATON, 10 CATHEDRAL ROAD, 600086</Data></Cell>
   </Row>
   <Row>
    <Cell><Data>NEW KASHMIR ARTS &amp; CRAFTS</Data></Cell>
    <Cell><Data>SPENCER PLAZA, G-60, 2ND PHASE,768 ANNA SALAI, 600002</Data></Cell>
   </Row>
   <Row>
    <Cell><Data>NATURALLY AUROVILLE BOUTIQUE</Data></Cell>
    <Cell><Data>30 KHADER NAWAZ KHAN ROAD, 600006</Data></Cell>
   </Row>
   <Row>
    <Cell><Data>SHABNAM ARTS</Data></Cell>
    <Cell><Data>SHOP 41-A, SPENCER PLAZA, 2ND FLOOR, 2ND PHASE,769 ANNASALAI MOUNT RD, 600002</Data></Cell>
   </Row>
   <Row>
    <Cell><Data>TOUSEEF HANDICRAFTS</Data></Cell>
    <Cell><Data>SHOP NO S-20B, SECOND FLOOR, SPENCER PLAZA PHASE-I,NO 769, MOUNT ROAD, 600002</Data></Cell>
   </Row>
   <Row>
    <Cell><Data>A B T MARUTI</Data></Cell>
    <Cell><Data>NO-102, MOUNT ROAD,GUINDY, 600032</Data></Cell>
   </Row>
   <Row>
    <Cell><Data>ROSHANLAL CLASSICS</Data></Cell>
    <Cell><Data>B-2, KHAZANA PLAZA, 36,CATHEDRAL ROAD,ROSHANLAL@VSNL.COM, 600086</Data></Cell>
   </Row>
   <Row>
    <Cell><Data>LIMRAS ENTERPRISES PRIVATE LTD</Data></Cell>
    <Cell><Data>NO 808, POONAMALLEE HIGH ROAD,KILPAUK, 600010</Data></Cell>
   </Row>
   <Row>
    <Cell><Data>WALI ARTS</Data></Cell>
    <Cell><Data>4, OTHAVADAI STREET,MAHABALIPURAM, 603104</Data></Cell>
   </Row>
   <Row>
    <Cell><Data>ZARGAR SONS</Data></Cell>
    <Cell><Data>11-C, OTHAVADAI STREET,MAHABALIPURAM, 603104</Data></Cell>
   </Row>
   <Row>
    <Cell><Data>P ORR &amp; SONS P LTD</Data></Cell>
    <Cell><Data>POST BOX 317, 855,ANNA SALAI,PORRSONS@VSNL.COM, 600002</Data></Cell>
   </Row>
   <Row>
    <Cell><Data>P ORR &amp; SONS P LTD</Data></Cell>
    <Cell><Data>14/A A BLOCK, 3RD AVENUE AARAI COMPLEX,ANNA NAGAR, 600102</Data></Cell>
   </Row>
   <Row>
    <Cell><Data>P ORR &amp; SONS P LTD</Data></Cell>
    <Cell><Data>2 R K MUTT ROAD, LUZ CORNER PICNIC PLAZA,MYLAPORE, 600004</Data></Cell>
   </Row>
   <Row>
    <Cell><Data>P ORR &amp; SONS P LTD</Data></Cell>
    <Cell><Data>KG VALLENICA, 28 1ST MAIN ROAD,GANDHI NAGAR, ADYAR, 600020</Data></Cell>
   </Row>
   <Row>
    <Cell><Data>HEBRON LITERATURE CENTRE</Data></Cell>
    <Cell><Data>53, PUSHPA NAGAR, 2ND STREET,NUNGAMBAKKAM, 600034</Data></Cell>
   </Row>
   <Row>
    <Cell><Data>SINGAPORE 2000</Data></Cell>
    <Cell><Data>NO 105, PAPER MILLS ROAD,PERAMBUR, 600011</Data></Cell>
   </Row>
   <Row>
    <Cell><Data>EVE'S</Data></Cell>
    <Cell><Data>SHOP G-11A, GROUND FLOOR, PHASE-1, SPENCER PLAZA,769, ANNA SALAI, 600002</Data></Cell>
   </Row>
   <Row>
    <Cell><Data>CASAMIA</Data></Cell>
    <Cell><Data>4TH FLOOR&quot;COROMANDEL TOWERS&quot;, 93, SANTHOME HIGH ROAD,KARPAGAM AVENUE, R.A. PURAM,SALES@ICLTEXTILES.COM, 600028</Data></Cell>
   </Row>
   <Row>
    <Cell><Data>AMMA NAANA</Data></Cell>
    <Cell><Data>NO.82, CAAMIERS ROAD,ALWARPET, 600018</Data></Cell>
   </Row>
   <Row>
    <Cell><Data>RUPRANG</Data></Cell>
    <Cell><Data>57, G N CHETTY ROAD,T NAGAR, 600017</Data></Cell>
   </Row>
   <Row>
    <Cell><Data>PERSIAN ART GALLERY</Data></Cell>
    <Cell><Data>SHOP NO F-47, FIRST FLOOR, SECOND PHASE,SPENCER PLAZA, 769, ANNA SALAI, 600002</Data></Cell>
   </Row>
   <Row>
    <Cell><Data>GEM N LEATHER SHOP</Data></Cell>
    <Cell><Data>INTERNATIONAL AIRPORT, MEENAMBAKKAM, 600027</Data></Cell>
   </Row>
   <Row>
    <Cell><Data>JANS ARCADE</Data></Cell>
    <Cell><Data>C/O LE ROYAL MERIDIEN, NO 1, G S T ROAD,ST THOMAS MOUNT, 600016</Data></Cell>
   </Row>
   <Row>
    <Cell><Data>LIBERTY SURGICAL CO</Data></Cell>
    <Cell><Data>NO. 62 OLD NO. 839, MOUNT ROAD, ANNA SALAI, 600002</Data></Cell>
   </Row>
   <Row>
    <Cell><Data>CLASSIC CRAFTS</Data></Cell>
    <Cell><Data>S 67 A, SPENCER PLAZA PHASE-II, 2ND FLOOR,768 ANNASALAI, 600002</Data></Cell>
   </Row>
   <Row>
    <Cell><Data>T MANGHARAM</Data></Cell>
    <Cell><Data>NO 49, RATTAN BAZAAR,BELANI@VSNL.COM, 600003</Data></Cell>
   </Row>
   <Row>
    <Cell><Data>XL TYRE POINT</Data></Cell>
    <Cell><Data>AH-20 SHANTHI COLONY, ANNA NAGAR, 600040</Data></Cell>
   </Row>
   <Row>
    <Cell><Data>HER CHOICE</Data></Cell>
    <Cell><Data>NO-1, B.K.G BUSINESS CENTRE,NO-34/65, TTK ROAD, ALWARPET, 600018</Data></Cell>
   </Row>
   <Row>
    <Cell><Data>BLUE HEAVEN</Data></Cell>
    <Cell><Data>SINGAPORE SHOPPING COMPLEX, PATNI PLAZA,90/41 N.S.C BOSE ROAD, 600079</Data></Cell>
   </Row>
   <Row>
    <Cell><Data>ORIENTAL TREASURES</Data></Cell>
    <Cell><Data>F-21B, SPENCER PLAZA, PHASE-I, FIRST FLOOR,769 ANNA SALAI, 600002</Data></Cell>
   </Row>
   <Row>
    <Cell><Data>WOVEN LEGENDS</Data></Cell>
    <Cell><Data>G-195 GROUND FLOOR, III PHASE, SPENCER PLAZA,769 MOUNT ROAD, 600002</Data></Cell>
   </Row>
   <Row>
    <Cell><Data>PUJAS</Data></Cell>
    <Cell><Data>NO 71, SIR THYAGARAYA ROAD, SHOP NO 30,31,MAYA'S PLAZA , T NAGAR, 600017</Data></Cell>
   </Row>
   <Row>
    <Cell><Data>WHITE FIELD NILGIRIS</Data></Cell>
    <Cell><Data>NO 55/16 ANNAI VELANCANNI, CHURCH ROAD,BESANT NAGAR, 600090</Data></Cell>
   </Row>
   <Row>
    <Cell><Data>FLEMINGO DUTY FREE SHOP</Data></Cell>
    <Cell><Data>CHENNAI INTERNATIONAL AIRPORT, ARIVAL LOUNGE,MEENAMBAKAM, 600027</Data></Cell>
   </Row>
   <Row>
    <Cell><Data>FOCUS GALLERY</Data></Cell>
    <Cell><Data>NO 59 T.T.K ROAD, ALWARPET, 600018</Data></Cell>
   </Row>
   <Row>
    <Cell><Data>SWETHAS</Data></Cell>
    <Cell><Data>HAYAGRIVAS BUILDING, 2ND FLOOR,153 ,G.N CHETTY ROAD,T NAGAR,SRINIVASSAREES@YAHOO.COM, 600017</Data></Cell>
   </Row>
   <Row>
    <Cell><Data>FRIENDS OFFSET CALENDARS</Data></Cell>
    <Cell><Data>#62/39, BUNDER STREET, 600001</Data></Cell>
   </Row>
   <Row>
    <Cell><Data>NEW ANCIENT ARTS GALLERY</Data></Cell>
    <Cell><Data>G-202, PHASE III, SPENCER PLAZA,769, ANNA SALAI, 600002</Data></Cell>
   </Row>
   <Row>
    <Cell><Data>PRIME ARTS</Data></Cell>
    <Cell><Data>SHOP#S-67-E, PHASE II SPENCER PLAZA,769 ANNASALAI, 600002</Data></Cell>
   </Row>
   <Row>
    <Cell><Data>JJ SINGAPORE SHOPPING</Data></Cell>
    <Cell><Data>FATHIMA PLAZA NO 78, PONDYBAZAR, SHOP # 16,17 1ST FLOOR,TNAGAR, 600017</Data></Cell>
   </Row>
   <Row>
    <Cell><Data>RANI ARTS AND TEAK</Data></Cell>
    <Cell><Data>NO 8, HARRINGTON ROAD,CHETPET, 600031</Data></Cell>
   </Row>
   <Row>
    <Cell><Data>RAJASTHAN EMPORIUM</Data></Cell>
    <Cell><Data>#G-204 PHASE-III, SPENCER PLAZA,769 ANNASALAI, 600002</Data></Cell>
   </Row>
   <Row>
    <Cell><Data>NEW DEEPAK'S</Data></Cell>
    <Cell><Data>SHOP NO 29 BASEMENT, GOKUL ARCADE NO 2,SARDAR PATEL ROAD ADYAR, 600020</Data></Cell>
   </Row>
   <Row>
    <Cell><Data>CHHOTABHAI RETAILING</Data></Cell>
    <Cell><Data>J-10,6TH AVENUE, ANNANAGAR EAST, 600102</Data></Cell>
   </Row>
   <Row>
    <Cell><Data>MAYAN HANDICRAFTS</Data></Cell>
    <Cell><Data>30-38, FIVE RATHAS ROAD, MAMALLAPURAM, 603104</Data></Cell>
   </Row>
   <Row>
    <Cell><Data>PONNUSAMY HOTEL</Data></Cell>
    <Cell><Data>NO 24 COMMANDER L N CHIEF ROAD, WELLINGDON ESTATE,OPP ETHIRAJ COLLEGE,EGMORE, 600105</Data></Cell>
   </Row>
   <Row>
    <Cell><Data>PONNUSAMY HOTEL</Data></Cell>
    <Cell><Data>RAHAT PLAZA, 1ST FLOOR,VADAPALANI, 600026</Data></Cell>
   </Row>
   <Row>
    <Cell><Data>PONNUSAMY HOTEL</Data></Cell>
    <Cell><Data>55/1, GOWDIYA MUTT ROAD,ROYAPETTAH,PONNUSAMYHOTELS@YAHOO.COM,4205283/114, 600014</Data></Cell>
   </Row>
   <Row>
    <Cell><Data>L'AMICALE THE GLOBAL LEISURE CLUB</Data></Cell>
    <Cell><Data>73/1,THIRUVALLUVAR SALAI, RAMAPURAM,LAMICALE@LAMICALE.NET,F22491220, 600089</Data></Cell>
   </Row>
   <Row>
    <Cell><Data>THE LEAGUE CLUB</Data></Cell>
    <Cell><Data>NO 105 VINAYAGAPURAM II STREET, ARUMBAKKAM,100 FT ROAD, 600106</Data></Cell>
   </Row>
   <Row>
    <Cell><Data>INSTORE</Data></Cell>
    <Cell><Data>38,SIR THIYAGARAYA ROAD,2ND &amp; 3RD FLR, PONDY BAZAR,T NAGAR,MAIL@INSTORE.CO.IN, 600017</Data></Cell>
   </Row>
   <Row>
    <Cell><Data>VILLAGE SQUARE</Data></Cell>
    <Cell><Data># 119 (65), DR RADHAKRISHNAN SALAI, MYLAPORE, 600004</Data></Cell>
   </Row>
   <Row>
    <Cell><Data>CASHMERE CRAFTS EMPORIUM</Data></Cell>
    <Cell><Data>S-34 IIND FLOOR II ND PHASE, 769 ANNA SALAI,MOUNT ROAD, 600002</Data></Cell>
   </Row>
   <Row>
    <Cell><Data>DEIVAM SILKS</Data></Cell>
    <Cell><Data>61, PONDY BAZAR,T NAGAR, 600017</Data></Cell>
   </Row>
   <Row>
    <Cell><Data>KOMAL</Data></Cell>
    <Cell><Data>NO 215, FOUNTAIN PLAZA,PANTHEON ROAD EGMORE, 600008</Data></Cell>
   </Row>
   <Row>
    <Cell><Data>SAIT TRADERS</Data></Cell>
    <Cell><Data># 54/5, MUTHULAKSHMI ROAD ( L B ROAD),ADYAR, 600020</Data></Cell>
   </Row>
   <Row>
    <Cell><Data>UNIQUE GIFTS</Data></Cell>
    <Cell><Data># S-101 IIND FLOOR, 3RD PHASE (NEAR ARCHIES),769, ANNA SALAI, 600002</Data></Cell>
   </Row>
   <Row>
    <Cell><Data>KASHMIR ART GALLERY</Data></Cell>
    <Cell><Data>SHOP NO. S-89, 3RD PHASE, 2ND FLOOR,SPENCER PLAZA, MOUNT ROAD,KASHMIRARTGALLERY@REDIFFMAIL.COM, 600002</Data></Cell>
   </Row>
   <Row>
    <Cell><Data>ROCKY AGENCIES</Data></Cell>
    <Cell><Data>NOKIA STORE, #550/136, HALLMARK TOWERS, T.T.K ROAD, ALWARPET,(BEHIND PARK SHERATON), 600018</Data></Cell>
   </Row>
   <Row>
    <Cell><Data>SURANG</Data></Cell>
    <Cell><Data>KHAZANA PLAZA, 36 BF/1,CATHEDRAL ROAD, 600086</Data></Cell>
   </Row>
   <Row>
    <Cell><Data>SWASTIK CAR JEWELS</Data></Cell>
    <Cell><Data>SHOP NO. 8, ALSA ARCADE, B-9, 2ND AVENUE,ANNA NAGAR (E), NEAR NAGAPPA MOTORS, 600102</Data></Cell>
   </Row>
   <Row>
    <Cell><Data>GLOBAL GIFT SOLUTIONS</Data></Cell>
    <Cell><Data>OLD# 38 (NEW# 122), NELSON MANICKAM ROAD,AMINJIKARAI, 600029</Data></Cell>
   </Row>
   <Row>
    <Cell><Data>HAND KRAFT TREASURES</Data></Cell>
    <Cell><Data>AC-148 SHANTHI COLONY 4TH AVENUE, ANNANAGAR CHENNAI, 600040</Data></Cell>
   </Row>
   <Row>
    <Cell><Data>COLLECTIONS UNIQUE</Data></Cell>
    <Cell><Data>NO-3,445,ARORA'S PLAZA, 110-EAST COAST ROAD,AKKARAI, 600119</Data></Cell>
   </Row>
   <Row>
    <Cell><Data>K.M.S DIGITAL CAMERA PALACE</Data></Cell>
    <Cell><Data>SPENCER PLAZA, F-204 1ST FLOOR 3RD PHASE,#769 SPENCER PLAZA ANNA SALAI, 600002</Data></Cell>
   </Row>
   <Row>
    <Cell><Data>KASHMIR EMPORIUM</Data></Cell>
    <Cell><Data>SPENCER PLAZA,S-17A 2ND FLOOR, 1ST PHASE SPENCER PLAZA,769 ANNA SALAI, 600002</Data></Cell>
   </Row>
   <Row>
    <Cell><Data>IDFS - DUTY FREE</Data></Cell>
    <Cell><Data>HP COMPLEX 1ST FLR NO.14 GN CHETTY, ROAD T NAGAR, 600042</Data></Cell>
   </Row>
   <Row>
    <Cell><Data>NATURALLY AUROVILLE BOUTIQUE</Data></Cell>
    <Cell><Data>64/38 KUKMANI STREET, KALAKSHETRA COLONY,BESANT NAGAR, 600090</Data></Cell>
   </Row>
   <Row>
    <Cell><Data>MAKOBA</Data></Cell>
    <Cell><Data>1-A JHAVER PLAZA NUNGAMBAKKAM, HIGH ROAD, 600034</Data></Cell>
   </Row>
   <Row>
    <Cell><Data>WRITESITE</Data></Cell>
    <Cell><Data>F130 1ST FLR PHASE-3, SPENCERS PLAZA,ANNA SALAI, 600002</Data></Cell>
   </Row>
   <Row>
    <Cell><Data>WRITESITE</Data></Cell>
    <Cell><Data>SHOP NO.13A,GROUND FLOOR, CHENNAI CITI CENTRE NO.10/11,DR RADHAKRISHNAN SALAI MYLAPORE, 600004</Data></Cell>
   </Row>
   <Row>
    <Cell><Data>WRITESITE</Data></Cell>
    <Cell><Data>F25 NO.26,GROUND FLOOR, ANNA NAGAR EAST, 600102</Data></Cell>
   </Row>
   <Row>
    <Cell><Data>SARANGI</Data></Cell>
    <Cell><Data>SARANGI, # 17-A, STERLING AVENUE, NUNGAMBAKKAM, 600034</Data></Cell>
   </Row>
   <Row>
    <Cell><Data>THE BOX</Data></Cell>
    <Cell><Data>NO-601, ANNASALAI, 600006</Data></Cell>
   </Row>
   <Row>
    <Cell><Data>NEW WORLD</Data></Cell>
    <Cell><Data>NEW DECOR TOWER, (BELOW ANJAPPAR HOTEL),DR.R.K. SALAI, 600004</Data></Cell>
   </Row>
   <Row>
    <Cell><Data>NEW WORLD</Data></Cell>
    <Cell><Data>1ST FLR,CHENNAI CITY CENTRE, MYLAPORE, 600004</Data></Cell>
   </Row>
   <Row>
    <Cell><Data>MIDAS TOUCH</Data></Cell>
    <Cell><Data>9 OTTHAVADAI CLOSS STREET, MAMALLAPURAM KANCHEEPURAM DISTRICT, 603104</Data></Cell>
   </Row>
   <Row>
    <Cell><Data>FLEMINGO DUTY FREE SHOP</Data></Cell>
    <Cell><Data>FLEMINGO DUTY FREE SHOP, K V APT IST FLOOR,NO 35 OLD NO 16 A POES GARDEN, 600086</Data></Cell>
   </Row>
   <Row>
    <Cell><Data>RANJANA ELECTRICALS</Data></Cell>
    <Cell><Data>NO-32 (OLD NO-147), NORTH USMAN ROAD,T NAGAR, 600017</Data></Cell>
   </Row>
   <Row>
    <Cell><Data>KARISHMA</Data></Cell>
    <Cell><Data>NEW NO 58, OLD# 28, NUNGAMBAKKAM HIGH ROAD, 600034</Data></Cell>
   </Row>
   <Row>
    <Cell><Data>MANN</Data></Cell>
    <Cell><Data>2-275, 5 TH AVENUE,ANNA NAGAR, 600040</Data></Cell>
   </Row>
   <Row>
    <Cell><Data>NELLAI READYMADE STORE</Data></Cell>
    <Cell><Data>NO2/100, MANNADY STREET, 600001</Data></Cell>
   </Row>
   <Row>
    <Cell><Data>NESA</Data></Cell>
    <Cell><Data>NO 175, ANGAPPANAICKEN STREET, 600001</Data></Cell>
   </Row>
   <Row>
    <Cell><Data>JATIN DIAMOND CO</Data></Cell>
    <Cell><Data>87 (OLD# 42), NSC BOSE ROAD, 600079</Data></Cell>
   </Row>
   <Row>
    <Cell><Data>HIBA SHOP</Data></Cell>
    <Cell><Data>17/10, THIRUVALLUVAR COLONY, K K NAGAR, 600078</Data></Cell>
   </Row>
   <Row>
    <Cell><Data>FRAULEN</Data></Cell>
    <Cell><Data>NO-AH-31,SHANTI COLONY ROAD, 4TH AVENUE,ANNA NAGAR, 600040</Data></Cell>
   </Row>
   <Row>
    <Cell><Data>JULLAAHA</Data></Cell>
    <Cell><Data>NO-8,J-BLOCK,6TH AVENUE, ANNA NAGAR EAST, 600102</Data></Cell>
   </Row>
   <Row>
    <Cell><Data>ROYCE</Data></Cell>
    <Cell><Data>AA 1,SHOP NO G 14 VSD PLAZA, ROUNTANA,ANNA NAGAR, 600040</Data></Cell>
   </Row>
   <Row>
    <Cell><Data>MENAKA CARD</Data></Cell>
    <Cell><Data>NO-227,KUTCHERY ROAD, MYLAPORE, 600004</Data></Cell>
   </Row>
   <Row>
    <Cell><Data>LIFE WORLD</Data></Cell>
    <Cell><Data># 66,PILLAYARKOVIL STREET, JAFFERKHANPET,NEAR VIJAYA THEATRE, 600083</Data></Cell>
   </Row>
   <Row>
    <Cell><Data>SUPER LAND</Data></Cell>
    <Cell><Data>NO 6,1ST MAIN ROAD, VIJAYA NAGAR,VELACHERY, 600042</Data></Cell>
   </Row>
   <Row>
    <Cell><Data>CELEBRATIONS</Data></Cell>
    <Cell><Data>NO-2, SOUTH BOAG ROAD,T NAGAR, 600017</Data></Cell>
   </Row>
   <Row>
    <Cell><Data>FOTO SPACE</Data></Cell>
    <Cell><Data>NO-1,CHANDER PLAZA,48/1 ARCOT ROAD, SALIGRAMAM, 600093</Data></Cell>
   </Row>
   <Row>
    <Cell><Data>KATARIAS SELECTION</Data></Cell>
    <Cell><Data>NO.45, CATHEDRAL ROAD 1ST FLOOR, OPP.STELLA MARIS COLLEGE., 600086</Data></Cell>
   </Row>
   <Row>
    <Cell><Data>CHHOTABHAI RETAILING</Data></Cell>
    <Cell><Data># 39,1ST MAIN ROAD, SASTRI NAGAR,ADAYAR, 600020</Data></Cell>
   </Row>
   <Row>
    <Cell><Data>ROYAL TOUCH</Data></Cell>
    <Cell><Data>S J B COMPLEX,27-C, THIRUVALLUVAR SALAI,3RD STREET,NESAPAKKAM,WEST K K NAGAR, 600078</Data></Cell>
   </Row>
   <Row>
    <Cell><Data>ASIAN CRAFTS EMPORIUM</Data></Cell>
    <Cell><Data>SPENCER PLAZA,NO 90,IIND PHASE, GROUND FLOOR,SPENCER PLAZA,MOUNT ROAD, 600002</Data></Cell>
   </Row>
   <Row>
    <Cell><Data>MOVIE CLUB</Data></Cell>
    <Cell><Data># AG-22, SHANTI COLONY, ANNA NAGAR, 600040</Data></Cell>
   </Row>
   <Row>
    <Cell><Data>MARUTHI SERVICE MASTERS</Data></Cell>
    <Cell><Data>MARUTHI SERVICE MASTERS, PLOT NO 9(SP),THIRU VI KA INDUSTRIAL,AREA,GUINDY, 600032</Data></Cell>
   </Row>
   <Row>
    <Cell><Data>CHHOTABHAI RETAILING</Data></Cell>
    <Cell><Data>#29,P.T RAJAN SALAI,KUMARAGURU, APPARTMENTS,K.K NAGAR, 600078</Data></Cell>
   </Row>
   <Row>
    <Cell><Data>SAHELI</Data></Cell>
    <Cell><Data>CL SONS COMPLEX OLD 150/41, NEW 2/62 GROUND FLOOR CLSONS COMPLEX,MONTTETH ROAD EGMORE, 600008</Data></Cell>
   </Row>
   <Row>
    <Cell><Data>SUNNY SISTEMS</Data></Cell>
    <Cell><Data>NO 58,2ND MAIN ROAD, GANDHI NAGAR,ADYAR, 600020</Data></Cell>
   </Row>
   <Row>
    <Cell><Data>AAVARANAA</Data></Cell>
    <Cell><Data>15, ASOKA STREET, ALWARPET, 600018</Data></Cell>
   </Row>
   <Row>
    <Cell ss:StyleID="s17"/>
    <Cell ss:StyleID="s17"/>
   </Row>
   <Row>
    <Cell ss:StyleID="s17"/>
    <Cell ss:StyleID="s17"/>
   </Row>
   <Row>
    <Cell ss:StyleID="s17"/>
    <Cell ss:StyleID="s17"/>
   </Row>
   <Row>
    <Cell ss:StyleID="s17"/>
    <Cell ss:StyleID="s17"/>
   </Row>
   <Row>
    <Cell ss:StyleID="s17"/>
    <Cell ss:StyleID="s17"/>
   </Row>
   <Row>
    <Cell ss:StyleID="s17"/>
    <Cell ss:StyleID="s17"/>
   </Row>
   <Row>
    <Cell ss:StyleID="s17"/>
    <Cell ss:StyleID="s17"/>
   </Row>
   <Row>
    <Cell ss:StyleID="s17"/>
    <Cell ss:StyleID="s17"/>
   </Row>
   <Row>
    <Cell ss:StyleID="s17"/>
    <Cell ss:StyleID="s17"/>
   </Row>
   <Row>
    <Cell ss:StyleID="s17"/>
    <Cell ss:StyleID="s17"/>
   </Row>
   <Row>
    <Cell ss:StyleID="s17"/>
    <Cell ss:StyleID="s17"/>
   </Row>
   <Row>
    <Cell ss:StyleID="s17"/>
    <Cell ss:StyleID="s17"/>
   </Row>
   <Row>
    <Cell ss:StyleID="s17"/>
    <Cell ss:StyleID="s17"/>
   </Row>
   <Row>
    <Cell ss:StyleID="s17"/>
    <Cell ss:StyleID="s17"/>
   </Row>
   <Row>
    <Cell ss:StyleID="s17"/>
    <Cell ss:StyleID="s17"/>
   </Row>
   <Row>
    <Cell ss:StyleID="s17"/>
    <Cell ss:StyleID="s17"/>
   </Row>
   <Row>
    <Cell ss:StyleID="s17"/>
    <Cell ss:StyleID="s17"/>
   </Row>
   <Row>
    <Cell ss:StyleID="s17"/>
    <Cell ss:StyleID="s17"/>
   </Row>
   <Row>
    <Cell ss:StyleID="s17"/>
    <Cell ss:StyleID="s17"/>
   </Row>
   <Row>
    <Cell ss:StyleID="s17"/>
    <Cell ss:StyleID="s17"/>
   </Row>
   <Row>
    <Cell ss:StyleID="s17"/>
    <Cell ss:StyleID="s17"/>
   </Row>
   <Row>
    <Cell ss:StyleID="s17"/>
    <Cell ss:StyleID="s17"/>
   </Row>
   <Row>
    <Cell ss:StyleID="s17"/>
    <Cell ss:StyleID="s17"/>
   </Row>
   <Row>
    <Cell ss:StyleID="s17"/>
    <Cell ss:StyleID="s17"/>
   </Row>
   <Row>
    <Cell ss:StyleID="s17"/>
    <Cell ss:StyleID="s17"/>
   </Row>
   <Row>
    <Cell ss:StyleID="s17"/>
    <Cell ss:StyleID="s17"/>
   </Row>
   <Row>
    <Cell ss:StyleID="s17"/>
    <Cell ss:StyleID="s17"/>
   </Row>
   <Row>
    <Cell ss:StyleID="s17"/>
    <Cell ss:StyleID="s17"/>
   </Row>
   <Row>
    <Cell ss:StyleID="s17"/>
    <Cell ss:StyleID="s17"/>
   </Row>
   <Row>
    <Cell ss:StyleID="s17"/>
    <Cell ss:StyleID="s17"/>
   </Row>
   <Row>
    <Cell ss:StyleID="s17"/>
    <Cell ss:StyleID="s17"/>
   </Row>
   <Row>
    <Cell ss:StyleID="s17"/>
    <Cell ss:StyleID="s17"/>
   </Row>
   <Row>
    <Cell ss:StyleID="s17"/>
    <Cell ss:StyleID="s17"/>
   </Row>
   <Row>
    <Cell ss:StyleID="s17"/>
    <Cell ss:StyleID="s17"/>
   </Row>
   <Row>
    <Cell ss:StyleID="s17"/>
    <Cell ss:StyleID="s17"/>
   </Row>
   <Row>
    <Cell ss:StyleID="s17"/>
    <Cell ss:StyleID="s17"/>
   </Row>
   <Row>
    <Cell ss:StyleID="s17"/>
    <Cell ss:StyleID="s17"/>
   </Row>
   <Row>
    <Cell ss:StyleID="s17"/>
    <Cell ss:StyleID="s17"/>
   </Row>
   <Row>
    <Cell ss:StyleID="s17"/>
    <Cell ss:StyleID="s17"/>
   </Row>
   <Row>
    <Cell ss:StyleID="s17"/>
    <Cell ss:StyleID="s17"/>
   </Row>
   <Row>
    <Cell ss:StyleID="s17"/>
    <Cell ss:StyleID="s17"/>
   </Row>
   <Row>
    <Cell ss:StyleID="s17"/>
    <Cell ss:StyleID="s17"/>
   </Row>
   <Row>
    <Cell ss:StyleID="s17"/>
    <Cell ss:StyleID="s17"/>
   </Row>
   <Row>
    <Cell ss:StyleID="s17"/>
    <Cell ss:StyleID="s17"/>
   </Row>
   <Row>
    <Cell ss:StyleID="s17"/>
    <Cell ss:StyleID="s17"/>
   </Row>
   <Row>
    <Cell ss:StyleID="s17"/>
    <Cell ss:StyleID="s17"/>
   </Row>
   <Row>
    <Cell ss:StyleID="s17"/>
    <Cell ss:StyleID="s17"/>
   </Row>
   <Row>
    <Cell ss:StyleID="s17"/>
    <Cell ss:StyleID="s17"/>
   </Row>
   <Row>
    <Cell ss:StyleID="s17"/>
    <Cell ss:StyleID="s17"/>
   </Row>
   <Row>
    <Cell ss:StyleID="s17"/>
    <Cell ss:StyleID="s17"/>
   </Row>
   <Row>
    <Cell ss:StyleID="s17"/>
    <Cell ss:StyleID="s17"/>
   </Row>
   <Row>
    <Cell ss:StyleID="s17"/>
    <Cell ss:StyleID="s17"/>
   </Row>
   <Row>
    <Cell ss:StyleID="s17"/>
    <Cell ss:StyleID="s17"/>
   </Row>
   <Row>
    <Cell ss:StyleID="s17"/>
    <Cell ss:StyleID="s17"/>
   </Row>
   <Row>
    <Cell ss:StyleID="s17"/>
    <Cell ss:StyleID="s17"/>
   </Row>
   <Row>
    <Cell ss:StyleID="s17"/>
    <Cell ss:StyleID="s17"/>
   </Row>
   <Row>
    <Cell ss:StyleID="s17"/>
    <Cell ss:StyleID="s17"/>
   </Row>
   <Row>
    <Cell ss:StyleID="s17"/>
    <Cell ss:StyleID="s17"/>
   </Row>
   <Row>
    <Cell ss:StyleID="s17"/>
    <Cell ss:StyleID="s17"/>
   </Row>
   <Row>
    <Cell ss:StyleID="s17"/>
    <Cell ss:StyleID="s17"/>
   </Row>
   <Row>
    <Cell ss:StyleID="s17"/>
    <Cell ss:StyleID="s17"/>
   </Row>
   <Row>
    <Cell ss:StyleID="s17"/>
    <Cell ss:StyleID="s17"/>
   </Row>
   <Row>
    <Cell ss:StyleID="s17"/>
    <Cell ss:StyleID="s17"/>
   </Row>
   <Row>
    <Cell ss:StyleID="s17"/>
    <Cell ss:StyleID="s17"/>
   </Row>
   <Row>
    <Cell ss:StyleID="s17"/>
    <Cell ss:StyleID="s17"/>
   </Row>
   <Row>
    <Cell ss:StyleID="s17"/>
    <Cell ss:StyleID="s17"/>
   </Row>
   <Row>
    <Cell ss:StyleID="s17"/>
    <Cell ss:StyleID="s17"/>
   </Row>
   <Row>
    <Cell ss:StyleID="s17"/>
    <Cell ss:StyleID="s17"/>
   </Row>
   <Row>
    <Cell ss:StyleID="s17"/>
    <Cell ss:StyleID="s17"/>
   </Row>
   <Row>
    <Cell ss:StyleID="s17"/>
    <Cell ss:StyleID="s17"/>
   </Row>
   <Row>
    <Cell ss:StyleID="s17"/>
    <Cell ss:StyleID="s17"/>
   </Row>
   <Row>
    <Cell ss:StyleID="s17"/>
    <Cell ss:StyleID="s17"/>
   </Row>
   <Row>
    <Cell ss:StyleID="s17"/>
    <Cell ss:StyleID="s17"/>
   </Row>
   <Row>
    <Cell ss:StyleID="s17"/>
    <Cell ss:StyleID="s17"/>
   </Row>
   <Row>
    <Cell ss:StyleID="s17"/>
    <Cell ss:StyleID="s17"/>
   </Row>
   <Row>
    <Cell ss:StyleID="s17"/>
    <Cell ss:StyleID="s17"/>
   </Row>
   <Row>
    <Cell ss:StyleID="s17"/>
    <Cell ss:StyleID="s17"/>
   </Row>
   <Row>
    <Cell ss:StyleID="s17"/>
    <Cell ss:StyleID="s17"/>
   </Row>
   <Row>
    <Cell ss:StyleID="s17"/>
    <Cell ss:StyleID="s17"/>
   </Row>
   <Row>
    <Cell ss:StyleID="s17"/>
    <Cell ss:StyleID="s17"/>
   </Row>
   <Row>
    <Cell ss:StyleID="s17"/>
    <Cell ss:StyleID="s17"/>
   </Row>
   <Row>
    <Cell ss:StyleID="s17"/>
    <Cell ss:StyleID="s17"/>
   </Row>
   <Row>
    <Cell ss:StyleID="s17"/>
    <Cell ss:StyleID="s17"/>
   </Row>
   <Row>
    <Cell ss:StyleID="s17"/>
    <Cell ss:StyleID="s17"/>
   </Row>
   <Row>
    <Cell ss:StyleID="s17"/>
    <Cell ss:StyleID="s17"/>
   </Row>
   <Row>
    <Cell ss:StyleID="s17"/>
    <Cell ss:StyleID="s17"/>
   </Row>
   <Row>
    <Cell ss:StyleID="s17"/>
    <Cell ss:StyleID="s17"/>
   </Row>
   <Row>
    <Cell ss:StyleID="s17"/>
    <Cell ss:StyleID="s17"/>
   </Row>
   <Row>
    <Cell ss:StyleID="s17"/>
    <Cell ss:StyleID="s17"/>
   </Row>
   <Row>
    <Cell ss:StyleID="s17"/>
    <Cell ss:StyleID="s17"/>
   </Row>
   <Row>
    <Cell ss:StyleID="s17"/>
    <Cell ss:StyleID="s17"/>
   </Row>
   <Row>
    <Cell ss:StyleID="s17"/>
    <Cell ss:StyleID="s17"/>
   </Row>
   <Row>
    <Cell ss:StyleID="s17"/>
    <Cell ss:StyleID="s17"/>
   </Row>
   <Row>
    <Cell ss:StyleID="s17"/>
    <Cell ss:StyleID="s17"/>
   </Row>
   <Row>
    <Cell ss:StyleID="s17"/>
    <Cell ss:StyleID="s17"/>
   </Row>
   <Row>
    <Cell ss:StyleID="s17"/>
    <Cell ss:StyleID="s17"/>
   </Row>
   <Row>
    <Cell ss:StyleID="s17"/>
    <Cell ss:StyleID="s17"/>
   </Row>
   <Row>
    <Cell ss:StyleID="s17"/>
    <Cell ss:StyleID="s17"/>
   </Row>
   <Row>
    <Cell ss:StyleID="s17"/>
    <Cell ss:StyleID="s17"/>
   </Row>
   <Row>
    <Cell ss:StyleID="s17"/>
    <Cell ss:StyleID="s17"/>
   </Row>
   <Row>
    <Cell ss:StyleID="s17"/>
    <Cell ss:StyleID="s17"/>
   </Row>
   <Row>
    <Cell ss:StyleID="s17"/>
    <Cell ss:StyleID="s17"/>
   </Row>
   <Row>
    <Cell ss:StyleID="s17"/>
    <Cell ss:StyleID="s17"/>
   </Row>
   <Row>
    <Cell ss:StyleID="s17"/>
    <Cell ss:StyleID="s17"/>
   </Row>
   <Row>
    <Cell ss:StyleID="s17"/>
    <Cell ss:StyleID="s17"/>
   </Row>
   <Row>
    <Cell ss:StyleID="s17"/>
    <Cell ss:StyleID="s17"/>
   </Row>
   <Row>
    <Cell ss:StyleID="s17"/>
    <Cell ss:StyleID="s17"/>
   </Row>
   <Row>
    <Cell ss:StyleID="s17"/>
    <Cell ss:StyleID="s17"/>
   </Row>
   <Row>
    <Cell ss:StyleID="s17"/>
    <Cell ss:StyleID="s17"/>
   </Row>
   <Row>
    <Cell ss:StyleID="s17"/>
    <Cell ss:StyleID="s17"/>
   </Row>
   <Row>
    <Cell ss:StyleID="s17"/>
    <Cell ss:StyleID="s17"/>
   </Row>
   <Row>
    <Cell ss:StyleID="s17"/>
    <Cell ss:StyleID="s17"/>
   </Row>
   <Row>
    <Cell ss:StyleID="s17"/>
    <Cell ss:StyleID="s17"/>
   </Row>
   <Row>
    <Cell ss:StyleID="s17"/>
    <Cell ss:StyleID="s17"/>
   </Row>
   <Row>
    <Cell ss:StyleID="s17"/>
    <Cell ss:StyleID="s17"/>
   </Row>
   <Row>
    <Cell ss:StyleID="s17"/>
    <Cell ss:StyleID="s17"/>
   </Row>
   <Row>
    <Cell ss:StyleID="s17"/>
    <Cell ss:StyleID="s17"/>
   </Row>
   <Row>
    <Cell ss:StyleID="s17"/>
    <Cell ss:StyleID="s17"/>
   </Row>
   <Row>
    <Cell ss:StyleID="s17"/>
    <Cell ss:StyleID="s17"/>
   </Row>
   <Row>
    <Cell ss:StyleID="s17"/>
    <Cell ss:StyleID="s17"/>
   </Row>
   <Row>
    <Cell ss:StyleID="s17"/>
    <Cell ss:StyleID="s17"/>
   </Row>
   <Row>
    <Cell ss:StyleID="s17"/>
    <Cell ss:StyleID="s17"/>
   </Row>
   <Row>
    <Cell ss:StyleID="s17"/>
    <Cell ss:StyleID="s17"/>
   </Row>
   <Row>
    <Cell ss:StyleID="s17"/>
    <Cell ss:StyleID="s17"/>
   </Row>
   <Row>
    <Cell ss:StyleID="s17"/>
    <Cell ss:StyleID="s17"/>
   </Row>
   <Row>
    <Cell ss:StyleID="s17"/>
    <Cell ss:StyleID="s17"/>
   </Row>
   <Row>
    <Cell ss:StyleID="s17"/>
    <Cell ss:StyleID="s17"/>
   </Row>
   <Row>
    <Cell ss:StyleID="s17"/>
    <Cell ss:StyleID="s17"/>
   </Row>
   <Row>
    <Cell ss:StyleID="s17"/>
    <Cell ss:StyleID="s17"/>
   </Row>
   <Row>
    <Cell ss:StyleID="s17"/>
    <Cell ss:StyleID="s17"/>
   </Row>
   <Row>
    <Cell ss:StyleID="s17"/>
    <Cell ss:StyleID="s17"/>
   </Row>
   <Row>
    <Cell ss:StyleID="s17"/>
    <Cell ss:StyleID="s17"/>
   </Row>
   <Row>
    <Cell ss:StyleID="s17"/>
    <Cell ss:StyleID="s17"/>
   </Row>
   <Row>
    <Cell ss:StyleID="s17"/>
    <Cell ss:StyleID="s17"/>
   </Row>
   <Row>
    <Cell ss:StyleID="s17"/>
    <Cell ss:StyleID="s17"/>
   </Row>
   <Row>
    <Cell ss:StyleID="s17"/>
    <Cell ss:StyleID="s17"/>
   </Row>
   <Row>
    <Cell ss:StyleID="s17"/>
    <Cell ss:StyleID="s17"/>
   </Row>
   <Row>
    <Cell ss:StyleID="s17"/>
    <Cell ss:StyleID="s17"/>
   </Row>
   <Row>
    <Cell ss:StyleID="s17"/>
    <Cell ss:StyleID="s17"/>
   </Row>
   <Row>
    <Cell ss:StyleID="s17"/>
    <Cell ss:StyleID="s17"/>
   </Row>
   <Row>
    <Cell ss:StyleID="s17"/>
    <Cell ss:StyleID="s17"/>
   </Row>
   <Row>
    <Cell ss:StyleID="s17"/>
    <Cell ss:StyleID="s17"/>
   </Row>
   <Row>
    <Cell ss:StyleID="s17"/>
    <Cell ss:StyleID="s17"/>
   </Row>
   <Row>
    <Cell ss:StyleID="s17"/>
    <Cell ss:StyleID="s17"/>
   </Row>
   <Row>
    <Cell ss:StyleID="s17"/>
    <Cell ss:StyleID="s17"/>
   </Row>
   <Row>
    <Cell ss:StyleID="s17"/>
    <Cell ss:StyleID="s17"/>
   </Row>
   <Row>
    <Cell ss:StyleID="s17"/>
    <Cell ss:StyleID="s17"/>
   </Row>
   <Row>
    <Cell ss:StyleID="s17"/>
    <Cell ss:StyleID="s17"/>
   </Row>
   <Row>
    <Cell ss:StyleID="s17"/>
    <Cell ss:StyleID="s17"/>
   </Row>
   <Row>
    <Cell ss:StyleID="s17"/>
    <Cell ss:StyleID="s17"/>
   </Row>
   <Row>
    <Cell ss:StyleID="s17"/>
    <Cell ss:StyleID="s17"/>
   </Row>
   <Row>
    <Cell ss:StyleID="s17"/>
    <Cell ss:StyleID="s17"/>
   </Row>
   <Row>
    <Cell ss:StyleID="s17"/>
    <Cell ss:StyleID="s17"/>
   </Row>
   <Row>
    <Cell ss:StyleID="s17"/>
    <Cell ss:StyleID="s17"/>
   </Row>
   <Row>
    <Cell ss:StyleID="s17"/>
    <Cell ss:StyleID="s17"/>
   </Row>
   <Row>
    <Cell ss:StyleID="s17"/>
    <Cell ss:StyleID="s17"/>
   </Row>
   <Row>
    <Cell ss:StyleID="s17"/>
    <Cell ss:StyleID="s17"/>
   </Row>
   <Row>
    <Cell ss:StyleID="s17"/>
    <Cell ss:StyleID="s17"/>
   </Row>
   <Row>
    <Cell ss:StyleID="s17"/>
    <Cell ss:StyleID="s17"/>
   </Row>
   <Row>
    <Cell ss:StyleID="s17"/>
    <Cell ss:StyleID="s17"/>
   </Row>
   <Row>
    <Cell ss:StyleID="s17"/>
    <Cell ss:StyleID="s17"/>
   </Row>
   <Row>
    <Cell ss:StyleID="s17"/>
    <Cell ss:StyleID="s17"/>
   </Row>
   <Row>
    <Cell ss:StyleID="s17"/>
    <Cell ss:StyleID="s17"/>
   </Row>
   <Row>
    <Cell ss:StyleID="s17"/>
    <Cell ss:StyleID="s17"/>
   </Row>
   <Row>
    <Cell ss:StyleID="s17"/>
    <Cell ss:StyleID="s17"/>
   </Row>
   <Row>
    <Cell ss:StyleID="s17"/>
    <Cell ss:StyleID="s17"/>
   </Row>
   <Row>
    <Cell ss:StyleID="s17"/>
    <Cell ss:StyleID="s17"/>
   </Row>
   <Row>
    <Cell ss:StyleID="s17"/>
    <Cell ss:StyleID="s17"/>
   </Row>
   <Row>
    <Cell ss:StyleID="s17"/>
    <Cell ss:StyleID="s17"/>
   </Row>
   <Row>
    <Cell ss:StyleID="s17"/>
    <Cell ss:StyleID="s17"/>
   </Row>
   <Row>
    <Cell ss:StyleID="s17"/>
    <Cell ss:StyleID="s17"/>
   </Row>
   <Row>
    <Cell ss:StyleID="s17"/>
    <Cell ss:StyleID="s17"/>
   </Row>
   <Row>
    <Cell ss:StyleID="s17"/>
    <Cell ss:StyleID="s17"/>
   </Row>
   <Row>
    <Cell ss:StyleID="s17"/>
    <Cell ss:StyleID="s17"/>
   </Row>
   <Row>
    <Cell ss:StyleID="s17"/>
    <Cell ss:StyleID="s17"/>
   </Row>
   <Row>
    <Cell ss:StyleID="s17"/>
    <Cell ss:StyleID="s17"/>
   </Row>
   <Row>
    <Cell ss:StyleID="s17"/>
    <Cell ss:StyleID="s17"/>
   </Row>
   <Row>
    <Cell ss:StyleID="s17"/>
    <Cell ss:StyleID="s17"/>
   </Row>
   <Row>
    <Cell ss:StyleID="s17"/>
    <Cell ss:StyleID="s17"/>
   </Row>
   <Row>
    <Cell ss:StyleID="s17"/>
    <Cell ss:StyleID="s17"/>
   </Row>
   <Row>
    <Cell ss:StyleID="s17"/>
    <Cell ss:StyleID="s17"/>
   </Row>
   <Row>
    <Cell ss:StyleID="s17"/>
    <Cell ss:StyleID="s17"/>
   </Row>
   <Row>
    <Cell ss:StyleID="s17"/>
    <Cell ss:StyleID="s17"/>
   </Row>
   <Row>
    <Cell ss:StyleID="s17"/>
    <Cell ss:StyleID="s17"/>
   </Row>
   <Row>
    <Cell ss:StyleID="s17"/>
    <Cell ss:StyleID="s17"/>
   </Row>
   <Row>
    <Cell ss:StyleID="s17"/>
    <Cell ss:StyleID="s17"/>
   </Row>
   <Row>
    <Cell ss:StyleID="s17"/>
    <Cell ss:StyleID="s17"/>
   </Row>
   <Row>
    <Cell ss:StyleID="s17"/>
    <Cell ss:StyleID="s17"/>
   </Row>
   <Row>
    <Cell ss:StyleID="s17"/>
    <Cell ss:StyleID="s17"/>
   </Row>
   <Row>
    <Cell ss:StyleID="s17"/>
    <Cell ss:StyleID="s17"/>
   </Row>
   <Row>
    <Cell ss:StyleID="s17"/>
    <Cell ss:StyleID="s17"/>
   </Row>
   <Row>
    <Cell ss:StyleID="s17"/>
    <Cell ss:StyleID="s17"/>
   </Row>
   <Row>
    <Cell ss:StyleID="s17"/>
    <Cell ss:StyleID="s17"/>
   </Row>
   <Row>
    <Cell ss:StyleID="s17"/>
    <Cell ss:StyleID="s17"/>
   </Row>
   <Row>
    <Cell ss:StyleID="s17"/>
    <Cell ss:StyleID="s17"/>
   </Row>
   <Row>
    <Cell ss:StyleID="s17"/>
    <Cell ss:StyleID="s17"/>
   </Row>
   <Row>
    <Cell ss:StyleID="s17"/>
    <Cell ss:StyleID="s17"/>
   </Row>
   <Row>
    <Cell ss:StyleID="s17"/>
    <Cell ss:StyleID="s17"/>
   </Row>
   <Row>
    <Cell ss:StyleID="s17"/>
    <Cell ss:StyleID="s17"/>
   </Row>
   <Row>
    <Cell ss:StyleID="s17"/>
    <Cell ss:StyleID="s17"/>
   </Row>
   <Row>
    <Cell ss:StyleID="s17"/>
    <Cell ss:StyleID="s17"/>
   </Row>
   <Row>
    <Cell ss:StyleID="s17"/>
    <Cell ss:StyleID="s17"/>
   </Row>
   <Row>
    <Cell ss:StyleID="s17"/>
    <Cell ss:StyleID="s17"/>
   </Row>
   <Row>
    <Cell ss:StyleID="s17"/>
    <Cell ss:StyleID="s17"/>
   </Row>
   <Row>
    <Cell ss:StyleID="s17"/>
    <Cell ss:StyleID="s17"/>
   </Row>
   <Row>
    <Cell ss:StyleID="s17"/>
    <Cell ss:StyleID="s17"/>
   </Row>
   <Row>
    <Cell ss:StyleID="s17"/>
    <Cell ss:StyleID="s17"/>
   </Row>
   <Row>
    <Cell ss:StyleID="s17"/>
    <Cell ss:StyleID="s17"/>
   </Row>
   <Row>
    <Cell ss:StyleID="s17"/>
    <Cell ss:StyleID="s17"/>
   </Row>
   <Row>
    <Cell ss:StyleID="s17"/>
    <Cell ss:StyleID="s17"/>
   </Row>
   <Row>
    <Cell ss:StyleID="s17"/>
    <Cell ss:StyleID="s17"/>
   </Row>
   <Row>
    <Cell ss:StyleID="s17"/>
    <Cell ss:StyleID="s17"/>
   </Row>
   <Row>
    <Cell ss:StyleID="s17"/>
    <Cell ss:StyleID="s17"/>
   </Row>
   <Row>
    <Cell ss:StyleID="s17"/>
    <Cell ss:StyleID="s17"/>
   </Row>
   <Row>
    <Cell ss:StyleID="s17"/>
    <Cell ss:StyleID="s17"/>
   </Row>
   <Row>
    <Cell ss:StyleID="s17"/>
    <Cell ss:StyleID="s17"/>
   </Row>
   <Row>
    <Cell ss:StyleID="s17"/>
    <Cell ss:StyleID="s17"/>
   </Row>
   <Row>
    <Cell ss:StyleID="s17"/>
    <Cell ss:StyleID="s17"/>
   </Row>
   <Row>
    <Cell ss:StyleID="s17"/>
    <Cell ss:StyleID="s17"/>
   </Row>
   <Row>
    <Cell ss:StyleID="s17"/>
    <Cell ss:StyleID="s17"/>
   </Row>
   <Row>
    <Cell ss:StyleID="s17"/>
    <Cell ss:StyleID="s17"/>
   </Row>
   <Row>
    <Cell ss:StyleID="s17"/>
    <Cell ss:StyleID="s17"/>
   </Row>
   <Row>
    <Cell ss:StyleID="s17"/>
    <Cell ss:StyleID="s17"/>
   </Row>
   <Row>
    <Cell ss:StyleID="s17"/>
    <Cell ss:StyleID="s17"/>
   </Row>
   <Row>
    <Cell ss:StyleID="s17"/>
    <Cell ss:StyleID="s17"/>
   </Row>
   <Row>
    <Cell ss:StyleID="s17"/>
    <Cell ss:StyleID="s17"/>
   </Row>
   <Row>
    <Cell ss:StyleID="s17"/>
    <Cell ss:StyleID="s17"/>
   </Row>
   <Row>
    <Cell ss:StyleID="s17"/>
    <Cell ss:StyleID="s17"/>
   </Row>
   <Row>
    <Cell ss:StyleID="s17"/>
    <Cell ss:StyleID="s17"/>
   </Row>
   <Row>
    <Cell ss:StyleID="s17"/>
    <Cell ss:StyleID="s17"/>
   </Row>
   <Row>
    <Cell ss:StyleID="s17"/>
    <Cell ss:StyleID="s17"/>
   </Row>
   <Row>
    <Cell ss:StyleID="s17"/>
    <Cell ss:StyleID="s17"/>
   </Row>
   <Row>
    <Cell ss:StyleID="s17"/>
    <Cell ss:StyleID="s17"/>
   </Row>
   <Row>
    <Cell ss:StyleID="s17"/>
    <Cell ss:StyleID="s17"/>
   </Row>
   <Row>
    <Cell ss:StyleID="s17"/>
    <Cell ss:StyleID="s17"/>
   </Row>
   <Row>
    <Cell ss:StyleID="s17"/>
    <Cell ss:StyleID="s17"/>
   </Row>
   <Row>
    <Cell ss:StyleID="s17"/>
    <Cell ss:StyleID="s17"/>
   </Row>
   <Row>
    <Cell ss:StyleID="s17"/>
    <Cell ss:StyleID="s17"/>
   </Row>
   <Row>
    <Cell ss:StyleID="s17"/>
    <Cell ss:StyleID="s17"/>
   </Row>
   <Row>
    <Cell ss:StyleID="s17"/>
    <Cell ss:StyleID="s17"/>
   </Row>
   <Row>
    <Cell ss:StyleID="s17"/>
    <Cell ss:StyleID="s17"/>
   </Row>
   <Row>
    <Cell ss:StyleID="s17"/>
    <Cell ss:StyleID="s17"/>
   </Row>
   <Row>
    <Cell ss:StyleID="s17"/>
    <Cell ss:StyleID="s17"/>
   </Row>
   <Row>
    <Cell ss:StyleID="s17"/>
    <Cell ss:StyleID="s17"/>
   </Row>
   <Row>
    <Cell ss:StyleID="s17"/>
    <Cell ss:StyleID="s17"/>
   </Row>
   <Row>
    <Cell ss:StyleID="s17"/>
    <Cell ss:StyleID="s17"/>
   </Row>
   <Row>
    <Cell ss:StyleID="s17"/>
    <Cell ss:StyleID="s17"/>
   </Row>
   <Row>
    <Cell ss:StyleID="s17"/>
    <Cell ss:StyleID="s17"/>
   </Row>
   <Row>
    <Cell ss:StyleID="s17"/>
    <Cell ss:StyleID="s17"/>
   </Row>
   <Row>
    <Cell ss:StyleID="s17"/>
    <Cell ss:StyleID="s17"/>
   </Row>
   <Row>
    <Cell ss:StyleID="s17"/>
    <Cell ss:StyleID="s17"/>
   </Row>
   <Row>
    <Cell ss:StyleID="s17"/>
    <Cell ss:StyleID="s17"/>
   </Row>
   <Row>
    <Cell ss:StyleID="s17"/>
    <Cell ss:StyleID="s17"/>
   </Row>
   <Row>
    <Cell ss:StyleID="s17"/>
    <Cell ss:StyleID="s17"/>
   </Row>
   <Row>
    <Cell ss:StyleID="s17"/>
    <Cell ss:StyleID="s17"/>
   </Row>
   <Row>
    <Cell ss:StyleID="s17"/>
    <Cell ss:StyleID="s17"/>
   </Row>
   <Row>
    <Cell ss:StyleID="s17"/>
    <Cell ss:StyleID="s17"/>
   </Row>
   <Row>
    <Cell ss:StyleID="s17"/>
    <Cell ss:StyleID="s17"/>
   </Row>
   <Row>
    <Cell ss:StyleID="s17"/>
    <Cell ss:StyleID="s17"/>
   </Row>
   <Row>
    <Cell ss:StyleID="s17"/>
    <Cell ss:StyleID="s17"/>
   </Row>
   <Row>
    <Cell ss:StyleID="s17"/>
    <Cell ss:StyleID="s17"/>
   </Row>
   <Row>
    <Cell ss:StyleID="s17"/>
    <Cell ss:StyleID="s17"/>
   </Row>
   <Row>
    <Cell ss:StyleID="s17"/>
    <Cell ss:StyleID="s17"/>
   </Row>
   <Row>
    <Cell ss:StyleID="s17"/>
    <Cell ss:StyleID="s17"/>
   </Row>
   <Row>
    <Cell ss:StyleID="s16"/>
    <Cell ss:StyleID="s16"/>
   </Row>
   <Row>
    <Cell ss:StyleID="s16"/>
    <Cell ss:StyleID="s16"/>
   </Row>
   <Row>
    <Cell ss:StyleID="s16"/>
    <Cell ss:StyleID="s16"/>
   </Row>
   <Row>
    <Cell ss:StyleID="s16"/>
    <Cell ss:StyleID="s16"/>
   </Row>
   <Row>
    <Cell ss:StyleID="s16"/>
    <Cell ss:StyleID="s16"/>
   </Row>
   <Row>
    <Cell ss:StyleID="s16"/>
    <Cell ss:StyleID="s16"/>
   </Row>
   <Row>
    <Cell ss:StyleID="s16"/>
    <Cell ss:StyleID="s16"/>
   </Row>
  </Table>
  <WorksheetOptions xmlns="urn:schemas-microsoft-com:office:excel">
   <PageSetup>
    <Header x:Margin="0.3"/>
    <Footer x:Margin="0.3"/>
    <PageMargins x:Bottom="0.75" x:Left="0.7" x:Right="0.7" x:Top="0.75"/>
   </PageSetup>
   <Selected/>
   <Panes>
    <Pane>
     <Number>3</Number>
     <ActiveRow>1</ActiveRow>
     <ActiveCol>1</ActiveCol>
    </Pane>
   </Panes>
   <ProtectObjects>False</ProtectObjects>
   <ProtectScenarios>False</ProtectScenarios>
  </WorksheetOptions>
 </Worksheet>
</Workbook>
